msplanner_tools/__init__.py
msplanner_tools/auth.py
msplanner_tools/buckets.py
msplanner_tools/plans.py
msplanner_tools/tasks.py
msplanner_tools/users.py
msplanner_tools-0.1.93.dist-info/LICENSE
msplanner_tools-0.1.93.dist-info/METADATA
msplanner_tools-0.1.93.dist-info/WHEEL
msplanner_tools-0.1.93.dist-info/top_level.txt
msplanner_tools-0.1.93.dist-info/RECORD
